[
  { "productId": 804222, "price": 49.99 },
  { "productId": 100201, "price": 19.99 },
  { "productId": 100202, "price": 27.45 },
  { "productId": 100203, "price": 34.99 },
  { "productId": 100204, "price": 59.89 },
  { "productId": 100205, "price": 12.99 },
  { "productId": 100206, "price": 42.75 },
  { "productId": 100207, "price": 77.3 },
  { "productId": 100208, "price": 66.0 },
  { "productId": 100209, "price": 22.5 },
  { "productId": 100210, "price": 36.1 },
  { "productId": 100211, "price": 15.75 },
  { "productId": 100212, "price": 63.4 },
  { "productId": 100213, "price": 11.25 },
  { "productId": 100214, "price": 85.99 },
  { "productId": 100215, "price": 26.79 },
  { "productId": 100216, "price": 54.3 },
  { "productId": 100217, "price": 32.19 },
  { "productId": 100218, "price": 29.9 },
  { "productId": 100219, "price": 47.65 },
  { "productId": 100220, "price": 17.99 },
  { "productId": 100221, "price": 70.0 },
  { "productId": 100222, "price": 89.75 },
  { "productId": 100223, "price": 45.55 },
  { "productId": 100224, "price": 19.25 },
  { "productId": 100225, "price": 28.9 },
  { "productId": 100226, "price": 49.0 },
  { "productId": 100227, "price": 58.99 },
  { "productId": 100228, "price": 23.45 },
  { "productId": 100229, "price": 14.99 },
  { "productId": 100230, "price": 76.89 },
  { "productId": 100231, "price": 55.55 },
  { "productId": 100232, "price": 64.0 },
  { "productId": 100233, "price": 37.9 },
  { "productId": 100234, "price": 10.0 },
  { "productId": 100235, "price": 21.49 },
  { "productId": 100236, "price": 18.99 },
  { "productId": 100237, "price": 60.0 },
  { "productId": 100238, "price": 81.25 },
  { "productId": 100239, "price": 33.5 },
  { "productId": 100240, "price": 44.99 },
  { "productId": 100241, "price": 39.9 },
  { "productId": 100242, "price": 12.49 },
  { "productId": 100243, "price": 53.0 },
  { "productId": 100244, "price": 30.25 },
  { "productId": 100245, "price": 17.5 },
  { "productId": 100246, "price": 41.2 },
  { "productId": 100247, "price": 67.89 },
  { "productId": 100248, "price": 25.0 },
  { "productId": 100249, "price": 86.3 }
]
